{
  "Textures": {
    "T_Rim_Cube": "Hotta/Content/Resources/CubeMap/N2.N2",
    "N2": "Hotta/Content/Resources/CubeMap/N2.N2",
    "PM_Diffuse": "Hotta/Content/Resources/Characters_Vera/player/female_01/SSR/mimicry_fashion_39L2/ter_hair/T_f_mimicry_fashion_39_L2_hair_04_d.T_f_mimicry_fashion_39_L2_hair_04_d",
    "BaseColor": "Hotta/Content/Resources/Characters_Vera/player/female_01/SSR/mimicry_fashion_39L2/ter_hair/T_f_mimicry_fashion_39_L2_hair_04_d.T_f_mimicry_fashion_39_L2_hair_04_d"
  },
  "Parameters": {
    "BlendMode": 5,
    "ShadingModel": 0,
    "Colors": {
      "SpecColor": {
        "R": 1.0,
        "G": 1.0,
        "B": 1.0,
        "A": 1.0,
        "Hex": "FFFFFFFF"
      },
      "SunColorMuti": {
        "R": 1.0,
        "G": 1.0,
        "B": 1.0,
        "A": 1.0,
        "Hex": "FFFFFFFF"
      },
      "ShadowColor": {
        "R": 0.948486,
        "G": 0.957459,
        "B": 0.984375,
        "A": 1.0,
        "Hex": "FFFAFBFE"
      },
      "CenterBaseColor": {
        "R": 1.0,
        "G": 1.0,
        "B": 1.0,
        "A": 1.0,
        "Hex": "FFFFFFFF"
      },
      "RimBaseColor": {
        "R": 1.0,
        "G": 0.822917,
        "B": 0.822917,
        "A": 1.0,
        "Hex": "FFFFEAEA"
      }
    },
    "Scalars": {
      "CubeRimIntensity": 1.580156,
      "RimFresnelBase": 2.739091,
      "BlinkHardness": 0.3,
      "BlinkSpeed": 0.0,
      "C_EmissiveIntensity": 1.0,
      "NormalMapScale": 1.0,
      "SpecSize": 0.02,
      "SpecIntensity": 0.1,
      "ShadowColorStrength": 1.2,
      "SunColorStrength": 1.0,
      "Offset": 0.5,
      "CenterTransparenct": 1.0,
      "RimTransparent": 1.0,
      "TransparentMultiply": 1.0,
      "RimExp": 10.0,
      "RefractionDepthBias": 0.0
    },
    "Switches": {
      "UseCubeHightLight": true
    },
    "Properties": {
      "bHasStaticPermutationResource": true,
      "BasePropertyOverrides": {
        "bOverride_OpacityMaskClipValue": true,
        "bOverride_BlendMode": true,
        "bOverride_ShadingModel": true,
        "bOverride_DitheredLODTransition": true,
        "bOverride_TwoSided": true,
        "BlendMode": "BLEND_AlphaComposite",
        "ShadingModel": "MSM_Unlit",
        "OpacityMaskClipValue": 0.3333
      }
    },
    "HasTopDiffuse": true,
    "HasTopNormals": false,
    "HasTopSpecularMasks": false,
    "HasTopEmissive": false,
    "IsTranslucent": false,
    "IsNull": false
  }
}